mijiaAPI/__init__.py
mijiaAPI/__main__.py
mijiaAPI/apis.py
mijiaAPI/devices.py
mijiaAPI/errors.py
mijiaAPI/logger.py
mijiaAPI/miutils.py
mijiaAPI/version.py
mijiaapi-3.0.5.dist-info/licenses/LICENSE
mijiaapi-3.0.5.dist-info/METADATA
mijiaapi-3.0.5.dist-info/WHEEL
mijiaapi-3.0.5.dist-info/entry_points.txt
mijiaapi-3.0.5.dist-info/top_level.txt
mijiaapi-3.0.5.dist-info/RECORD
