Metadata-Version: 2.4
Name: mijiaAPI
Version: 3.0.5
Summary: A Python API for Xiaomi Mijia
Author-email: Do1e <i@do1e.cn>
License-Expression: GPL-3.0-or-later
Project-URL: Homepage, https://github.com/Do1e/mijia-api
Project-URL: Repository, https://github.com/Do1e/mijia-api
Classifier: Programming Language :: Python :: 3
Classifier: Operating System :: OS Independent
Requires-Python: <4.0,>=3.9
License-File: LICENSE
Requires-Dist: pillow>=11.3.0
Requires-Dist: pycryptodome>=3.23.0
Requires-Dist: qrcode>=8.2
Requires-Dist: requests>=2.32.5
Requires-Dist: tzlocal>=5.3.1
Dynamic: license-file
